out_workspace-0.0.10.dist-info/licenses/LICENSE
ow/__init__.py
ow/py.typed
ow/cli/__init__.py
ow/cli/__main__.py
ow/cli/options.py
ow/cli/utils.py
ow/cli/version.py
ow/data/__init__.py
ow/data/mcp/agent.md
ow/mcp/__init__.py
ow/mcp/__main__.py
ow/mcp/install.py
ow/mcp/types.py
ow/mcp/utils.py
ow/mcp/cli/__init__.py
ow/mcp/cli/__main__.py
ow/mcp/cli/development.py
ow/mcp/cli/install.py
ow/workspace/__init__.py
ow/workspace/model.py
ow/workspace/utils.py
ow/workspace/cli/__init__.py
ow/workspace/cli/__main__.py
ow/workspace/cli/initialize.py
ow/workspace/cli/list.py
ow/workspace/mcp/__init__.py
ow/workspace/mcp/initialize.py
ow/workspace/mcp/resources.py
ow/workspace/mcp/tools.py
ow/workspace/tools/create.py
ow/workspace/tools/list.py
out_workspace-0.0.10.dist-info/METADATA
out_workspace-0.0.10.dist-info/WHEEL
out_workspace-0.0.10.dist-info/entry_points.txt
out_workspace-0.0.10.dist-info/top_level.txt
out_workspace-0.0.10.dist-info/RECORD
