Metadata-Version: 2.4
Name: out-workspace
Version: 0.0.10
Summary: Package for managing workspaces in out folder.
Author-email: Peter Pak <ppak10@gmail.com>
Project-URL: Homepage, https://github.com/ppak10/out-workspace
Project-URL: Issues, https://github.com/ppak10/out-workspace/issues
Requires-Python: >=3.10
License-File: LICENSE
Requires-Dist: mcp>=1.14.0
Requires-Dist: pydantic>=2.11.9
Requires-Dist: rich>=14.1.0
Requires-Dist: typer>=0.17.4
Dynamic: license-file
